MANIFEST.in
README
setup.cfg
setup.py
FinvoiceLib.egg-info/PKG-INFO
FinvoiceLib.egg-info/SOURCES.txt
FinvoiceLib.egg-info/dependency_links.txt
FinvoiceLib.egg-info/entry_points.txt
FinvoiceLib.egg-info/not-zip-safe
FinvoiceLib.egg-info/requires.txt
FinvoiceLib.egg-info/top_level.txt
finvoicelib/__init__.py
finvoicelib/error.py
finvoicelib/main.py
finvoicelib/mapping.py
finvoicelib/soap_envelope.py
finvoicelib/wrapper.py
finvoicelib/elements/__init__.py
finvoicelib/elements/buyer.py
finvoicelib/elements/country.py
finvoicelib/elements/delivery.py
finvoicelib/elements/element.py
finvoicelib/elements/epi.py
finvoicelib/elements/finvoice_root.py
finvoicelib/elements/invoice.py
finvoicelib/elements/invoice_row.py
finvoicelib/elements/seller.py
finvoicelib/elements/specification.py
finvoicelib/elements/subinvoice_row.py
finvoicelib/reader/__init__.py
finvoicelib/reader/finvoice_reader.py
finvoicelib/reader/message.py
finvoicelib/reader/xml_reader.py
finvoicelib/resources/Finvoice.dtd
finvoicelib/resources/Finvoice.xsd
finvoicelib/resources/Finvoice.xsl
finvoicelib/resources/Finvoice_peruslasku_kehystetty.xml
finvoicelib/resources/Pulli_laaja_20041215.xml
finvoicelib/resources/Pulli_laaja_20041215_no_soapenv.xml
finvoicelib/tests/__init__.py
finvoicelib/tests/test_error.py
finvoicelib/tests/test_mapping.py
finvoicelib/tests/test_soap_envelope.py
finvoicelib/tests/test_wrapper.py
finvoicelib/tests/elements/__init__.py
finvoicelib/tests/elements/test_buyer.py
finvoicelib/tests/elements/test_country.py
finvoicelib/tests/elements/test_delivery.py
finvoicelib/tests/elements/test_element.py
finvoicelib/tests/elements/test_epi.py
finvoicelib/tests/elements/test_finvoice_root.py
finvoicelib/tests/elements/test_invoice.py
finvoicelib/tests/elements/test_invoice_row.py
finvoicelib/tests/elements/test_seller.py
finvoicelib/tests/elements/test_specification.py
finvoicelib/tests/elements/test_subinvoice_row.py
finvoicelib/tests/reader/__init__.py
finvoicelib/tests/reader/test_message.py
finvoicelib/tests/reader/test_reader.py
finvoicelib/tests/reader/test_xml_reader.py