Metadata-Version: 1.0
Name: FinvoiceLib
Version: 0.1.13
Summary: A library for reading Finvoice XML files
Home-page: http://en.norfello.com/
Author: Norfello Oy
Author-email: opensource@norfello.com
License: BSD
Keywords: finvoice norfello postita.fi
Platform: UNKNOWN
Classifier: Development Status :: 3 - Alpha
Classifier: Intended Audience :: Developers
Classifier: Intended Audience :: Financial and Insurance Industry
Classifier: License :: OSI Approved :: BSD License
Classifier: Programming Language :: Python
Classifier: Topic :: Office/Business
